pyosintleak/__init__.py
pyosintleak/config.json
pyosintleak/cli/__init__.py
pyosintleak-1.0.2.dist-info/METADATA
pyosintleak-1.0.2.dist-info/WHEEL
pyosintleak-1.0.2.dist-info/entry_points.txt
pyosintleak-1.0.2.dist-info/top_level.txt
pyosintleak-1.0.2.dist-info/RECORD
