Metadata-Version: 2.1
Name: pyosintleak
Version: 1.0.2
Summary: pyosintleak is a library designed for utilizing the osintleak API, facilitating integration and automation of open-source intelligence operations.
Home-page: https://github.com/osintleak/pyosintleak
Download-URL: https://github.com/osintleak/pyosintleak/archive/v1.0.2.zip
Author: OsintLeak
Author-email: help@osintleak.com
Keywords: osintleak,osint,leak,breach,search,ol,pentesting
Classifier: Development Status :: 5 - Production/Stable
Classifier: Intended Audience :: Developers
Classifier: Intended Audience :: Information Technology
Classifier: Operating System :: OS Independent
Classifier: Topic :: Security
Classifier: Programming Language :: Python :: 3
Requires-Python: >=3
Requires-Dist: requests
Requires-Dist: colorama
